{
  "created": "2026-04-24T08:39:42.649088+00:00",
  "modified": "2026-04-24T08:39:42.744419+00:00",
  "id": 19728062,
  "conceptrecid": "19728061",
  "metadata": {
    "title": "Reality Vector: Environmental State Representation for Constrained AI Systems",
    "publication_date": "2026-04-24",
    "description": "Reality Vector defines the formal mechanism by which intelligent systems maintain a bounded, accurate representation of external environmental state. Rather than unbounded world models, Reality Vectors encode only the constraint-relevant subset of environmental parameters, updated via constrained sensor feeds with explicit uncertainty bounds. This paper provides the mathematical formalism, update semantics, and environmental intelligence modeling framework for bounded reality representation.",
    "access_right": "open",
    "creators": [
      {
        "name": "Blanco, Brodib L.",
        "affiliation": "Bxthre3 Inc"
      }
    ],
    "keywords": [
      "BX3 Framework",
      "intelligent systems",
      "deterministic AI",
      "bounded cognition",
      "human accountability",
      "AgentOS",
      "Bxthre3"
    ],
    "license": "cc-by-4.0",
    "imprint_publisher": "Zenodo",
    "notes": "Draft submission \u2014 not peer reviewed.",
    "upload_type": "publication",
    "publication_type": "article",
    "prereserve_doi": {
      "doi": "10.5281/zenodo.19728062",
      "recid": 19728062
    }
  },
  "title": "Reality Vector: Environmental State Representation for Constrained AI Systems",
  "links": {
    "self": "https://zenodo.org/api/deposit/depositions/19728062",
    "html": "https://zenodo.org/deposit/19728062",
    "badge": "https://zenodo.org/badge/doi/.svg",
    "files": "https://zenodo.org/api/deposit/depositions/19728062/files",
    "bucket": "https://zenodo.org/api/files/f360a59a-b1a2-4621-9d55-f8db7a7cc36b",
    "latest_draft": "https://zenodo.org/api/deposit/depositions/19728062",
    "latest_draft_html": "https://zenodo.org/deposit/19728062",
    "publish": "https://zenodo.org/api/deposit/depositions/19728062/actions/publish",
    "edit": "https://zenodo.org/api/deposit/depositions/19728062/actions/edit",
    "discard": "https://zenodo.org/api/deposit/depositions/19728062/actions/discard",
    "newversion": "https://zenodo.org/api/deposit/depositions/19728062/actions/newversion"
  },
  "record_id": 19728062,
  "owner": 1611520,
  "files": [],
  "state": "unsubmitted",
  "submitted": false
}